qeview/__init__.py
qeview/qe_analyse_FM.py
qeview/qe_analyse_PM.py
qeview/qe_base.py
qeview/wannier_loader.py
qeview-1.0.6.dist-info/LICENCE.txt
qeview-1.0.6.dist-info/METADATA
qeview-1.0.6.dist-info/WHEEL
qeview-1.0.6.dist-info/top_level.txt
qeview-1.0.6.dist-info/RECORD
