Metadata-Version: 2.2
Name: qeview
Version: 1.0.6
Summary: Quantum Espresso Analysis and Visualization Tool 
Home-page: https://github.com/EgorcaA/QEView
Download-URL: https://github.com/EgorcaA/QEView/archive/main.zip
Author: EgorcaA
Author-email: agapov.em@phystech.edu
License: MIT License, see LICENSE file
Classifier: License :: OSI Approved :: Apache Software License
Classifier: Operating System :: OS Independent
Classifier: Intended Audience :: End Users/Desktop
Classifier: Intended Audience :: Developers
Classifier: Programming Language :: Python
Classifier: Programming Language :: Python :: 3
Classifier: Programming Language :: Python :: 3.6
Classifier: Programming Language :: Python :: 3.7
Classifier: Programming Language :: Python :: 3.8
Classifier: Programming Language :: Python :: Implementation :: PyPy
Classifier: Programming Language :: Python :: Implementation :: CPython
License-File: LICENCE.txt
Requires-Dist: qeschema
Requires-Dist: tqdm
Requires-Dist: matplotlib
Requires-Dist: numpy
Dynamic: author
Dynamic: author-email
Dynamic: classifier
Dynamic: description
Dynamic: description-content-type
Dynamic: download-url
Dynamic: home-page
Dynamic: license
Dynamic: requires-dist
Dynamic: summary
